_afg2lp.cpython-311-darwin.so
_vbpsol.cpython-311-darwin.so
_vbp2afg.cpython-311-darwin.so
_afg2ampl.cpython-311-darwin.so
_afg2mps.cpython-311-darwin.so
pyvpsolver-3.1.4.data/scripts/vpsolver_glpk.sh
pyvpsolver-3.1.4.data/scripts/vpsolver_base.sh
pyvpsolver-3.1.4.data/scripts/vpsolver_coinor.sh
pyvpsolver-3.1.4.data/scripts/vbp2afg
pyvpsolver-3.1.4.data/scripts/settings.json
pyvpsolver-3.1.4.data/scripts/vpsolver_scip.sh
pyvpsolver-3.1.4.data/scripts/vbpsol
pyvpsolver-3.1.4.data/scripts/afg2ampl
pyvpsolver-3.1.4.data/scripts/afg2mps
pyvpsolver-3.1.4.data/scripts/afg2lp
pyvpsolver-3.1.4.data/scripts/afg2svg
pyvpsolver-3.1.4.data/scripts/vpsolver_lpsolve.sh
pyvpsolver-3.1.4.data/scripts/vpsolver_cplex.sh
pyvpsolver-3.1.4.data/scripts/vpsolver_ampl.sh
pyvpsolver-3.1.4.data/scripts/vpsolver_gurobi.sh
pyvpsolver/vpsolver.py
pyvpsolver/__init__.py
pyvpsolver/utils.py
pyvpsolver/afgraph.py
pyvpsolver/webapp/__init__.py
pyvpsolver/webapp/app.py
pyvpsolver/webapp/static/favicon.ico
pyvpsolver/webapp/static/bootstrap/css/bootstrap.min.css
pyvpsolver/webapp/static/bootstrap/css/bootstrap.css
pyvpsolver/webapp/static/bootstrap/css/bootstrap-theme-readable.css
pyvpsolver/webapp/static/bootstrap/css/bootstrap.css.map
pyvpsolver/webapp/static/bootstrap/css/bootstrap-theme.css.map
pyvpsolver/webapp/static/bootstrap/css/bootstrap-theme.css
pyvpsolver/webapp/static/bootstrap/css/bootstrap-theme.min.css
pyvpsolver/webapp/static/bootstrap/js/npm.js
pyvpsolver/webapp/static/bootstrap/js/bootstrap.js
pyvpsolver/webapp/static/bootstrap/js/bootstrap.min.js
pyvpsolver/webapp/static/bootstrap/fonts/glyphicons-halflings-regular.woff
pyvpsolver/webapp/static/bootstrap/fonts/glyphicons-halflings-regular.eot
pyvpsolver/webapp/static/bootstrap/fonts/glyphicons-halflings-regular.woff2
pyvpsolver/webapp/static/bootstrap/fonts/glyphicons-halflings-regular.ttf
pyvpsolver/webapp/static/bootstrap/fonts/glyphicons-halflings-regular.svg
pyvpsolver-3.1.4.dist-info/RECORD
pyvpsolver-3.1.4.dist-info/LICENSE
pyvpsolver-3.1.4.dist-info/WHEEL
pyvpsolver-3.1.4.dist-info/top_level.txt
pyvpsolver-3.1.4.dist-info/METADATA
