Metadata-Version: 2.1
Name: pyvpsolver
Version: 3.1.4
Summary: Arc-flow Vector Packing Solver (VPSolver)
Home-page: https://github.com/fdabrandao/vpsolver
Author: Filipe Brandao
Author-email: fdabrandao@gmail.com
Maintainer: Filipe Brandao
Maintainer-email: fdabrandao@gmail.com
License: BSD-3
Platform: unix
Platform: linux
Platform: osx
Classifier: Development Status :: 5 - Production/Stable
Classifier: Intended Audience :: Science/Research
Classifier: Programming Language :: Python
Classifier: Programming Language :: Python :: 3
Classifier: License :: OSI Approved :: BSD License
Classifier: Topic :: Scientific/Engineering
License-File: LICENSE
Requires-Dist: future (>=0.15.0)
Requires-Dist: six (>=1.5.2)
Requires-Dist: flask (>=0.10.1)
Requires-Dist: pympl (>=1.1.2)
Requires-Dist: pytest (>=2.9.1)
Requires-Dist: pytest-cov (>=2.2.1)
Requires-Dist: coveralls (>=1.1)
